topsis_101703189_garvita_chhabra-1.0.0.dist-info/METADATA
topsis_101703189_garvita_chhabra-1.0.0.dist-info/RECORD
topsis_101703189_garvita_chhabra-1.0.0.dist-info/WHEEL
topsis_101703189_garvita_chhabra-1.0.0.dist-info/entry_points.txt
topsis_101703189_garvita_chhabra-1.0.0.dist-info/top_level.txt
topsis_python/topsis.py
